{
  "account_id": "ACC_003",
  "company_name": "PacWest Fire and Safety",
  "changelog_generated_at": "2026-03-03T11:25:29.446313Z",
  "v1_source": "demo_call",
  "v2_source": "onboarding_call",
  "total_changes": 6,
  "critical_changes": 4,
  "minor_changes": 2,
  "changes": {
    "critical": [
      {
        "field": "emergency_definition",
        "change_type": "list_updated",
        "v1_value": [
          "Active fire on site",
          "Suppression system activation"
        ],
        "v2_value": [
          "Active fire on site",
          "Suppression system activation",
          "CO detector alarm"
        ],
        "added_items": [
          "CO detector alarm"
        ],
        "removed_items": [],
        "note": "List updated in onboarding"
      },
      {
        "field": "integration_constraints",
        "change_type": "list_updated",
        "v1_value": [
          "Quickbooks integration in use \u2014 see constraints above",
          "Google Calendar integration in use \u2014 see constraints above"
        ],
        "v2_value": [
          "All job creation in ServiceTrade/ServiceTitan must be done manually",
          "Do not provide pricing quotes to callers",
          "Do not book or schedule appointments directly",
          "Google Calendar integration in use \u2014 see constraints above"
        ],
        "added_items": [
          "All job creation in ServiceTrade/ServiceTitan must be done manually",
          "Do not provide pricing quotes to callers",
          "Do not book or schedule appointments directly"
        ],
        "removed_items": [
          "Quickbooks integration in use \u2014 see constraints above"
        ],
        "note": "List updated in onboarding"
      },
      {
        "field": "non_emergency_routing_rules",
        "change_type": "updated",
        "v1_value": null,
        "v2_value": "Collect name, phone number, and description. Confirm follow-up during next business hours. Do not attempt transfer.",
        "significance": "critical",
        "note": "Confirmed in onboarding call \u2014 overrides demo assumption"
      },
      {
        "field": "services_supported",
        "change_type": "list_updated",
        "v1_value": [
          "Inspections",
          "Hood Suppression Systems",
          "Sprinkler Systems",
          "Fire Extinguisher Service"
        ],
        "v2_value": [
          "Inspections",
          "Hood Suppression Systems",
          "Fire Extinguisher Service"
        ],
        "added_items": [],
        "removed_items": [
          "Sprinkler Systems"
        ],
        "note": "List updated in onboarding"
      }
    ],
    "minor": [
      {
        "field": "version",
        "change_type": "added",
        "v1_value": null,
        "v2_value": "v2",
        "note": "New field added in onboarding"
      },
      {
        "field": "version_history",
        "change_type": "added",
        "v1_value": null,
        "v2_value": {
          "v1_generated_at": "2026-03-03T11:25:29.388770Z",
          "v2_generated_at": "2026-03-03T11:25:29.446224Z"
        },
        "note": "New field added in onboarding"
      }
    ]
  }
}